MANIFEST.in
README.md
UNLICENSE
setup.cfg
setup.py
src/pyramid_alchemy/__init__.py
src/pyramid_alchemy/directive.py
src/pyramid_alchemy.egg-info/PKG-INFO
src/pyramid_alchemy.egg-info/SOURCES.txt
src/pyramid_alchemy.egg-info/dependency_links.txt
src/pyramid_alchemy.egg-info/not-zip-safe
src/pyramid_alchemy.egg-info/requires.txt
src/pyramid_alchemy.egg-info/top_level.txt